mcp_vector_search/__init__.py
mcp_vector_search/server.py
mcp_vector_search_nepavel-1.0.7.dist-info/METADATA
mcp_vector_search_nepavel-1.0.7.dist-info/WHEEL
mcp_vector_search_nepavel-1.0.7.dist-info/entry_points.txt
mcp_vector_search_nepavel-1.0.7.dist-info/licenses/LICENSE
mcp_vector_search_nepavel-1.0.7.dist-info/RECORD
