Metadata-Version: 2.4
Name: mcp-vector-search-nepavel
Version: 1.0.7
Summary: MCP server for cloud-based vector code search
Project-URL: Homepage, https://github.com/NePavel221/mcp-vector-search
Project-URL: Repository, https://github.com/NePavel221/mcp-vector-search
Author-email: NePavel <your-email@example.com>
License: MIT
License-File: LICENSE
Keywords: ai,code-search,mcp,vector-search
Classifier: Development Status :: 4 - Beta
Classifier: Intended Audience :: Developers
Classifier: License :: OSI Approved :: MIT License
Classifier: Programming Language :: Python :: 3
Classifier: Programming Language :: Python :: 3.8
Classifier: Programming Language :: Python :: 3.9
Classifier: Programming Language :: Python :: 3.10
Classifier: Programming Language :: Python :: 3.11
Requires-Python: >=3.8
Requires-Dist: requests>=2.31.0
